<?xml version="1.0" encoding="utf-8"?>
<!DOCTYPE hibernate-mapping PUBLIC "-//Hibernate/Hibernate Mapping DTD 3.0//EN"
"D:\MyEclipse\Common\plugins\com.genuitec.eclipse.j2eedt.core_10.5.0.me201207171805\catalog-dtd\hibernate-mapping-3.0.dtd  ">
<!-- 
    Mapping file autogenerated by MyEclipse Persistence Tools
-->
<hibernate-mapping>
    <class name="cn.com.pojo.Userinfo3" table="USERINFO3" schema="LEJIA">
        <id name="UId" type="java.lang.Long">
            <column name="U_ID" precision="11" scale="0" />
               <generator class="sequence" >
            <param name="sequence">seq_userinfo3</param>
            
            </generator>
        </id>
        <property name="UTel" type="java.lang.Long">
            <column name="U_TEL" precision="11" scale="0" not-null="true" />
        </property>
        <property name="UPwd" type="java.lang.String">
            <column name="U_PWD" length="50" not-null="true" />
        </property>
        <property name="UCard" type="java.lang.Long">
            <column name="U_CARD" precision="18" scale="0" />
        </property>
        <property name="UAdr" type="java.lang.String">
            <column name="U_ADR" length="50" />
        </property>
        <property name="UQq" type="java.lang.Long">
            <column name="U_QQ" precision="13" scale="0" />
        </property>
        <property name="UEmail" type="java.lang.String">
            <column name="U_EMAIL" length="50" />
        </property>
        <property name="UName" type="java.lang.String">
            <column name="U_NAME" length="25" />
        </property> 
        <property name="USex" type="java.lang.String">
            <column name="U_SEX" length="3" />
        </property>
        <property name="UAdmin" type="java.lang.String">
            <column name="U_ADMIN" length="25" />
        </property>
        
    </class>
</hibernate-mapping>
